.DS_Store
climaticai/__init__.py
climaticai/__main__.py
climaticai/exceptions/__init__.py
climaticai/exceptions/exceptions.py
climaticai/model_family/__init__.py
climaticai/model_family/model_family.py
climaticai/model_family/utils.py
climaticai/objectives/__init__.py
climaticai/objectives/binary_classification_objective.py
climaticai/objectives/cost_benefit_matrix.py
climaticai/objectives/fraud_cost.py
climaticai/objectives/lead_scoring.py
climaticai/objectives/multiclass_classification_objective.py
climaticai/objectives/objective_base.py
climaticai/objectives/regression_objective.py
climaticai/objectives/sensitivity_low_alert.py
climaticai/objectives/standard_metrics.py
climaticai/objectives/time_series_regression_objective.py
climaticai/objectives/utils.py
climaticai/pipelines/__init__.py
climaticai/pipelines/binary_classification_pipeline.py
climaticai/pipelines/binary_classification_pipeline_mixin.py
climaticai/pipelines/classification_pipeline.py
climaticai/pipelines/component_graph.py
climaticai/pipelines/multiclass_classification_pipeline.py
climaticai/pipelines/pipeline_base.py
climaticai/pipelines/pipeline_meta.py
climaticai/pipelines/regression_pipeline.py
climaticai/pipelines/time_series_classification_pipelines.py
climaticai/pipelines/time_series_pipeline_base.py
climaticai/pipelines/time_series_regression_pipeline.py
climaticai/pipelines/utils.py
climaticai/pipelines/components/__init__.py
climaticai/pipelines/components/component_base.py
climaticai/pipelines/components/component_base_meta.py
climaticai/pipelines/components/utils.py
climaticai/pipelines/components/ensemble/__init__.py
climaticai/pipelines/components/ensemble/sklearn_stacked_ensemble_base.py
climaticai/pipelines/components/ensemble/sklearn_stacked_ensemble_classifier.py
climaticai/pipelines/components/ensemble/sklearn_stacked_ensemble_regressor.py
climaticai/pipelines/components/estimators/__init__.py
climaticai/pipelines/components/estimators/estimator.py
climaticai-1.33.0.dist-info/LICENSE
climaticai-1.33.0.dist-info/METADATA
climaticai-1.33.0.dist-info/WHEEL
climaticai-1.33.0.dist-info/entry_points.txt
climaticai-1.33.0.dist-info/top_level.txt
climaticai-1.33.0.dist-info/RECORD
