Metadata-Version: 2.1
Name: climaticai
Version: 1.33.0
Summary: climaticai is a library that builds, optimizes, and evaluates machine learning pipelines
Home-page: https://github.com/climatic-ai/climaticai
Author: Climatic Ai
Author-email: mike@climatic.ai
License: UNKNOWN
Platform: UNKNOWN
Requires-Dist: numpy (>=1.20.0)
Requires-Dist: numba (==0.53)
Requires-Dist: pandas (>=1.2.5)
Requires-Dist: scipy (>=1.5.0)
Requires-Dist: scikit-learn (>=0.24.0)
Requires-Dist: scikit-optimize (>=0.8.1)
Requires-Dist: pyzmq (>=20.0.0)
Requires-Dist: colorama (>=0.4.4)
Requires-Dist: cloudpickle (>=1.6.0)
Requires-Dist: click (>=7.1.2)
Requires-Dist: psutil (>=5.6.6)
Requires-Dist: requirements-parser (>=0.2.0)
Requires-Dist: shap (>=0.36.0)
Requires-Dist: texttable (>=1.6.2)
Requires-Dist: woodwork (<=0.8.1,>=0.6.0)
Requires-Dist: dask (==2021.7.0)
Requires-Dist: optuna (==2.3.0)
Requires-Dist: dask-optuna
Requires-Dist: dask-ml
Requires-Dist: featuretools (>=0.26.1)
Requires-Dist: nlp-primitives (>=1.1.0)
Requires-Dist: networkx (<2.6,>=2.5)
Requires-Dist: plotly (>=5.0.0)
Requires-Dist: kaleido (>=0.1.0)
Requires-Dist: ipywidgets (>=7.5)
Requires-Dist: xgboost (>=1.4.2)
Requires-Dist: lightgbm (>=2.3.1)
Requires-Dist: matplotlib (>=3.3.3)
Requires-Dist: seaborn (>=0.11.1)
Requires-Dist: category-encoders (>=2.2.2)
Requires-Dist: statsmodels (>=0.12.2)
Requires-Dist: imbalanced-learn (>=0.8.0)
Requires-Dist: pmdarima (==1.8.0)
Requires-Dist: graphviz (>=0.13) ; platform_system != "Windows"
Requires-Dist: sktime (>=0.7.0) ; python_version < "3.9"
Provides-Extra: complete
Requires-Dist: alteryx-open-src-update-checker (>=2.0.0) ; extra == 'complete'
Requires-Dist: cmdstan-builder (==0.0.4) ; extra == 'complete'
Provides-Extra: prophet
Requires-Dist: cmdstan-builder (==0.0.4) ; extra == 'prophet'
Provides-Extra: update_checker
Requires-Dist: alteryx-open-src-update-checker (>=2.0.0) ; extra == 'update_checker'
